setup.cfg
setup.py
pyprojectgen.egg-info/PKG-INFO
pyprojectgen.egg-info/SOURCES.txt
pyprojectgen.egg-info/dependency_links.txt
pyprojectgen.egg-info/entry_points.txt
pyprojectgen.egg-info/requires.txt
pyprojectgen.egg-info/top_level.txt
scripts/__init__.py
scripts/generate_project.py
scripts/generate_template.py
src/__init__.py
src/file_folder_creators.py
src/gitignore_generator.py
src/license_generator.py
src/license_templates.py
src/metadata.py
src/metadata_generator.py
src/noserc_generator.py
src/project_config.py
src/project_generator.py
src/project_structure_generator.py
src/readme_generator.py
src/setup_generator.py
src/template_builder.py
src/tox_generator.py
tests/__init__.py
tests/test_helpers.py
tests/test_project_config.py
tests/test_project_generator.py
tests/test_template_builder.py