Metadata-Version: 1.1
Name: pyprojectgen
Version: 0.0.3
Summary: Generates python project structure.
Home-page: https://github.com/mjalas/pyprojectgen
Author: Mats Jalas
Author-email: mats.jalas@gmail.com
License: GNU GPLv3
Platform: UNKNOWN
Classifier: Development Status :: 3 - Alpha
Classifier: Intended Audience :: Developers
Classifier: Topic :: Software Development :: Libraries
Classifier: License :: OSI Approved :: MIT License
Classifier: Programming Language :: Python :: 3.5
